pytermor/__init__.py
pytermor/__main__.py
pytermor/_version.py
pytermor/ansi.py
pytermor/border.py
pytermor/color.py
pytermor/common.py
pytermor/config.py
pytermor/cval.py
pytermor/cval.py.tpl
pytermor/exception.py
pytermor/filter.py
pytermor/numfmt.py
pytermor/renderer.py
pytermor/style.py
pytermor/template.py
pytermor/term.py
pytermor/text.py
pytermor-2.108.0.dist-info/METADATA
pytermor-2.108.0.dist-info/WHEEL
pytermor-2.108.0.dist-info/licenses/LICENSE
pytermor-2.108.0.dist-info/RECORD
