Metadata-Version: 2.1
Name: pytermor
Version: 2.108.0
Summary: ANSI formatted terminal output toolset
Project-URL: Homepage, https://github.com/delameter/pytermor
Project-URL: Bug Tracker, https://github.com/delameter/pytermor/issues
Project-URL: Changelog, https://github.com/delameter/pytermor/blob/master/CHANGES.md
Author-email: Aleksandr Shavykin <0.delameter@gmail.com>
License-Expression: LGPL-3.0
License-File: LICENSE
Keywords: ansi,color,console,format,terminal
Classifier: Development Status :: 5 - Production/Stable
Classifier: Intended Audience :: Developers
Classifier: Intended Audience :: System Administrators
Classifier: License :: OSI Approved :: GNU Lesser General Public License v3 (LGPLv3)
Classifier: Operating System :: OS Independent
Classifier: Programming Language :: Python
Classifier: Programming Language :: Python :: 3
Classifier: Programming Language :: Python :: 3.8
Classifier: Programming Language :: Python :: 3.9
Classifier: Programming Language :: Python :: 3.10
Classifier: Topic :: Software Development :: Libraries
Classifier: Topic :: Text Processing :: Filters
Classifier: Topic :: Text Processing :: General
Requires-Python: >=3.8
